FFT/FFT.py
FFT/__init__.py
MFDFA_neural/__init__.py
MFDFA_neural/mfdfa_neural.py
STFTsignal/STFTsignal.py
STFTsignal/__init__.py
frequency_maximum_power/__init__.py
frequency_maximum_power/frequency_maximum_power.py
frequency_maximum_power/.ipynb_checkpoints/frequency_maximum_power-checkpoint.py
higuch_fractal_dimension/__init__.py
higuch_fractal_dimension/higuchi_fractal.py
phase_space_2d/__init__.py
phase_space_2d/phase_space.py
phase_space_3d/__init__.py
phase_space_3d/phase_space3d.py
spectral_centroids/__init__.py
spectral_centroids/spectral_centroids.py
spectral_edge_density/__init__.py
spectral_edge_density/spectral_edge_density.py
spectral_entropy_signals/__init__.py
spectral_entropy_signals/spectral_entropy_signals.py
transfer_entropy_all_signals/__init__.py
transfer_entropy_all_signals/transfer_entropy_regional.py
transfer_entropy_hemispheric/__init__.py
transfer_entropy_hemispheric/transfer_entropy_hemispheric.py
transfer_entropy_regional/__init__.py
transfer_entropy_regional/transfer_entropy_regional.py
welchsPSD/__init__.py
welchsPSD/welchsPSD.py
neural_signal_analysis-0.2.8.dist-info/LICENSE.md
neural_signal_analysis-0.2.8.dist-info/METADATA
neural_signal_analysis-0.2.8.dist-info/WHEEL
neural_signal_analysis-0.2.8.dist-info/top_level.txt
neural_signal_analysis-0.2.8.dist-info/RECORD
