Metadata-Version: 2.1
Name: neural-signal-analysis
Version: 0.2.8
Summary: A comprehensive Python library for human brain/ cortical organoid/spheroid eeg/ecog/mea data analysis including FFT, Higuchi Fractal Dimension, Transfer Entropy, and more.
Home-page: https://soulsyrup.github.io/
Author: soul_syrup
Author-email: soul.syrup@yandex.com
Classifier: Development Status :: 3 - Alpha
Classifier: Intended Audience :: Developers
Classifier: Topic :: Scientific/Engineering :: Information Analysis
Classifier: License :: OSI Approved :: MIT License
Classifier: Programming Language :: Python :: 3
Classifier: Programming Language :: Python :: 3.7
Classifier: Programming Language :: Python :: 3.8
Classifier: Programming Language :: Python :: 3.9
License-File: LICENSE.md
Requires-Dist: numpy
Requires-Dist: scipy
Requires-Dist: matplotlib
Requires-Dist: minepy
Requires-Dist: pyinform
